pycodelens/__init__.py
pycodelens/__main__.py
pycodelens/analyzer.py
pycodelens/cli.py
pycodelens-0.2.1.dist-info/licenses/LICENSE
pycodelens-0.2.1.dist-info/METADATA
pycodelens-0.2.1.dist-info/WHEEL
pycodelens-0.2.1.dist-info/entry_points.txt
pycodelens-0.2.1.dist-info/top_level.txt
pycodelens-0.2.1.dist-info/RECORD
